fast_chromedriver_manager/__init__.py
fast_chromedriver_manager/fast_chromedriver_manager.py
fast_chromedriver_manager/test_fast_chromedriver_manager.py
fast_chromedriver_manager-1.0.6.dist-info/LICENSE
fast_chromedriver_manager-1.0.6.dist-info/METADATA
fast_chromedriver_manager-1.0.6.dist-info/WHEEL
fast_chromedriver_manager-1.0.6.dist-info/top_level.txt
fast_chromedriver_manager-1.0.6.dist-info/RECORD
